scalewiz/__init__.py
scalewiz/__main__.py
scalewiz/components/__init__.py
scalewiz/components/evaluation_data_view.py
scalewiz/components/evaluation_plot_view.py
scalewiz/components/evaluation_window.py
scalewiz/components/handler_view.py
scalewiz/components/handler_view_controls.py
scalewiz/components/handler_view_devices_entry.py
scalewiz/components/handler_view_info_entry.py
scalewiz/components/handler_view_plot.py
scalewiz/components/icon.ico
scalewiz/components/project_editor.py
scalewiz/components/project_editor_info.py
scalewiz/components/project_editor_params.py
scalewiz/components/project_editor_report.py
scalewiz/components/scalewiz.py
scalewiz/components/scalewiz_log_window.py
scalewiz/components/scalewiz_main_frame.py
scalewiz/components/scalewiz_menu_bar.py
scalewiz/components/scalewiz_rinse_window.py
scalewiz/helpers/__init__.py
scalewiz/helpers/configuration.py
scalewiz/helpers/export.py
scalewiz/helpers/get_resource.py
scalewiz/helpers/score.py
scalewiz/helpers/set_icon.py
scalewiz/helpers/show_help.py
scalewiz/helpers/sort_nicely.py
scalewiz/helpers/validation.py
scalewiz/models/__init__.py
scalewiz/models/project.py
scalewiz/models/test.py
scalewiz/models/test_handler.py
scalewiz-0.5.13.dist-info/entry_points.txt
scalewiz-0.5.13.dist-info/COPYING
scalewiz-0.5.13.dist-info/WHEEL
scalewiz-0.5.13.dist-info/METADATA
scalewiz-0.5.13.dist-info/RECORD
