Metadata-Version: 2.1
Name: scalewiz
Version: 0.5.13
Summary: A graphical user interface for chemical performance testing designed to work with Teledyne SSI MX-class HPLC pumps.
Home-page: https://github.com/pct-code/scalewiz
License: GPL-3.0
Author: Alex Whittington
Author-email: alex@southsun.tech
Requires-Python: >=3.9,<4.0
Classifier: Development Status :: 4 - Beta
Classifier: Framework :: Matplotlib
Classifier: License :: OSI Approved :: GNU General Public License v3 (GPLv3)
Classifier: Programming Language :: Python :: 3
Classifier: Programming Language :: Python :: 3.10
Classifier: Programming Language :: Python :: 3.9
Classifier: Topic :: Scientific/Engineering
Classifier: Topic :: Scientific/Engineering :: Interface Engine/Protocol Translator
Classifier: Topic :: System :: Hardware :: Universal Serial Bus (USB)
Classifier: Topic :: Terminals :: Serial
Requires-Dist: appdirs (>=1.4.4,<2.0.0)
Requires-Dist: matplotlib (>=3.4.2,<4.0.0)
Requires-Dist: pandas (>=1.2.2,<2.0.0)
Requires-Dist: py-hplc (>=1.0.1,<2.0.0)
Requires-Dist: tkcalendar (>=1.6.1,<2.0.0)
Requires-Dist: tomlkit (>=0.7.0,<0.8.0)
Project-URL: Repository, https://github.com/pct-code/scalewiz
